xaal/__init__.py
xaal/mqttlogger/__init__.py
xaal/mqttlogger/__main__.py
xaal/mqttlogger/dev.py
xaal_mqttlogger-0.1.2.dist-info/METADATA
xaal_mqttlogger-0.1.2.dist-info/WHEEL
xaal_mqttlogger-0.1.2.dist-info/top_level.txt
xaal_mqttlogger-0.1.2.dist-info/RECORD
